{"metadata": {"dbt_schema_version": "https://schemas.getdbt.com/dbt/run-results/v4.json", "dbt_version": "1.5.4", "generated_at": "2023-08-02T14:25:34.620138Z", "invocation_id": "7496584f-4914-45c0-a733-0aa18507df6c", "env": {}}, "results": [{"status": "success", "timing": [{"name": "compile", "started_at": "2023-08-02T14:25:33.896781Z", "completed_at": "2023-08-02T14:25:33.905051Z"}, {"name": "execute", "started_at": "2023-08-02T14:25:33.905698Z", "completed_at": "2023-08-02T14:25:34.505880Z"}], "thread_id": "Thread-1 (worker)", "execution_time": 0.7200360298156738, "adapter_response": {"_message": "SUCCESS 1", "code": "SUCCESS", "rows_affected": 1, "query_id": "01ae0a41-0000-231e-0000-589900014172"}, "message": "SUCCESS 1", "failures": null, "unique_id": "model.refactoring_for_modularity.fct_customer_orders"}], "elapsed_time": 2.102710008621216, "args": {"select": ["fct_customer_orders"], "cache_selected_only": false, "defer": false, "macro_debugging": false, "version_check": true, "log_path": "/Users/andremoleiro/Documents/Learning/learning-repo/dbt/dbt_exam_preparation/dbt_projects/refactoring_for_modularity/refactoring_for_modularity/logs", "log_level_file": "debug", "send_anonymous_usage_stats": true, "printer_width": 80, "quiet": false, "vars": {}, "static_parser": true, "favor_state": false, "log_level": "info", "partial_parse": true, "populate_cache": true, "enable_legacy_logger": false, "exclude": [], "strict_mode": false, "resource_types": [], "which": "build", "indirect_selection": "eager", "write_json": true, "log_format_file": "debug", "print": true, "show": false, "use_colors_file": true, "warn_error_options": {"include": [], "exclude": []}, "log_format": "default", "project_dir": "/Users/andremoleiro/Documents/Learning/learning-repo/dbt/dbt_exam_preparation/dbt_projects/refactoring_for_modularity/refactoring_for_modularity", "profiles_dir": "/Users/andremoleiro/.dbt", "introspect": true, "use_colors": true}}